[
  {
    "text": "ホーム",
    "href": "/"
  },
  {
    "text": "",
    "menu": [
      {
        "text": "Darwin Core",
        "href": "/リスト/"
      },
      {
        "text": ""
      },
      {
        "text": "",
        "href": ""
      },
      {
        "text": "",
        "href": ""
      },
      {
        "text": ""
      },
      {
        "text": "",
        "href": ""
      },
      {
        "text": "",
        "href": ""
      },
      {
        "text": "",
        "href": ""
      }
    ]
  },
  {
    "text": "",
    "menu": [
      {
        "text": "",
        "href": ""
      },
      {
        "text": ""
      },
      {
        "text": "",
        "href": ""
      },
      {
        "text": "",
        "href": ""
      },
      {
        "text": ""
      },
      {
        "text": "",
        "href": ""
      },
      {
        "text": "",
        "href": ""
      },
      {
        "text": "",
        "href": ""
      },
      {
        "text": "",
        "href": ""
      },
      {
        "text": "",
        "href": ""
      },
      {
        "text": ""
      },
      {
        "text": "",
        "href": ""
      }
    ]
  },
  {
    "text": "",
    "href": ""
  },
  {
    "text": "",
    "menu": [
      {
        "text": "",
        "href": "/"
      },
      {
        "text": "",
        "href": ""
      },
      {
        "text": "",
        "href": ""
      }
    ]
  }
]
